perfsize/__init__.py
perfsize/environment/__init__.py
perfsize/environment/mock.py
perfsize/load/__init__.py
perfsize/load/mock.py
perfsize/perfsize.py
perfsize/py.typed
perfsize/reporter/__init__.py
perfsize/reporter/mock.py
perfsize/result/__init__.py
perfsize/result/gatling.py
perfsize/result/mock.py
perfsize/step/__init__.py
perfsize/step/all.py
perfsize/step/mock.py
perfsize-0.1.11.dist-info/LICENSE
perfsize-0.1.11.dist-info/WHEEL
perfsize-0.1.11.dist-info/METADATA
perfsize-0.1.11.dist-info/RECORD
