Metadata-Version: 2.1
Name: perfsize
Version: 0.1.11
Summary: Automated performance testing to determine the right size of infrastructure
Author: Richard Shiao
Requires-Python: >=3.8.11,<4.0.0
Classifier: Programming Language :: Python :: 3
Classifier: Programming Language :: Python :: 3.9
Requires-Dist: PyYAML (>=5.4.1,<6.0.0)
Requires-Dist: numpy (>=1.20.3,<2.0.0)
Requires-Dist: pandas (>=1.2.4,<2.0.0)
